flowkit/__init__.py
flowkit/_version.py
flowkit/core.py
flowkit/decorators.py
flowkit_async-1.0.0.dist-info/licenses/LICENSE
flowkit_async-1.0.0.dist-info/METADATA
flowkit_async-1.0.0.dist-info/WHEEL
flowkit_async-1.0.0.dist-info/top_level.txt
flowkit_async-1.0.0.dist-info/RECORD
