Metadata-Version: 2.4
Name: flowkit-async
Version: 1.0.0
Summary: Fluent async workflows with lazy execution for Python
Author-email: FlowKit Contributors <contributors@flowkit.dev>
Maintainer-email: FlowKit Contributors <contributors@flowkit.dev>
License-Expression: MIT
Project-URL: Homepage, https://github.com/flowkit/flowkit
Project-URL: Documentation, https://flowkit.readthedocs.io
Project-URL: Repository, https://github.com/flowkit/flowkit
Project-URL: Bug Tracker, https://github.com/flowkit/flowkit/issues
Keywords: async,workflow,simplification,http,api
Classifier: Development Status :: 4 - Beta
Classifier: Intended Audience :: Developers
Classifier: Programming Language :: Python :: 3
Classifier: Programming Language :: Python :: 3.8
Classifier: Programming Language :: Python :: 3.9
Classifier: Programming Language :: Python :: 3.10
Classifier: Programming Language :: Python :: 3.11
Classifier: Programming Language :: Python :: 3.12
Classifier: Topic :: Internet :: WWW/HTTP
Classifier: Topic :: Software Development :: Libraries :: Python Modules
Classifier: Framework :: AsyncIO
Requires-Python: >=3.8
License-File: LICENSE
Requires-Dist: httpx>=0.28.0
Requires-Dist: anyio>=4.0.0
Provides-Extra: fastapi
Requires-Dist: fastapi>=0.104.0; extra == "fastapi"
Provides-Extra: django
Requires-Dist: django>=4.2.0; extra == "django"
Provides-Extra: flask
Requires-Dist: flask>=2.3.0; extra == "flask"
Provides-Extra: dev
Requires-Dist: pytest>=7.0.0; extra == "dev"
Requires-Dist: pytest-asyncio>=0.21.0; extra == "dev"
Requires-Dist: hypothesis>=6.80.0; extra == "dev"
Requires-Dist: pytest-cov>=4.1.0; extra == "dev"
Requires-Dist: black>=23.0.0; extra == "dev"
Requires-Dist: ruff>=0.1.0; extra == "dev"
Requires-Dist: mypy>=1.7.0; extra == "dev"
Requires-Dist: pre-commit>=3.5.0; extra == "dev"
Dynamic: license-file
